<Properties StartupConfiguration="{E1456745-ED92-4EB6-8905-E64DC1E47277}|">
  <MonoDevelop.Ide.Workbench ActiveDocument="Assets/Scripts/Countdown.cs">
    <Files>
      <File FileName="Assets/Scripts/UIManager.cs" Line="27" Column="5" IsPinned="True" />
      <File FileName="Assets/Scripts/CharacterController2D.cs" Line="1" Column="1" />
      <File FileName="Assets/Scripts/PlayerController.cs" Line="170" Column="43" />
      <File FileName="Assets/Scripts/CameraController.cs" Line="1" Column="1" />
      <File FileName="Assets/Scripts/Countdown.cs" Line="9" Column="40" />
      <File FileName="Assets/Scripts/CollapsingPlatform.cs" Line="1" Column="1" />
      <File FileName="Assets/Scripts/Effectors.cs" Line="1" Column="1" />
      <File FileName="Assets/Scripts/Global.cs" Line="1" Column="1" />
      <File FileName="../../../../../Applications/Unity/Hub/Editor/2019.2.11f1/Unity.app/Contents/Resources/PackageManager/BuiltInPackages/com.unity.ugui/Runtime/UI/Core/GraphicRaycaster.cs" Line="1" Column="1" />
      <File FileName="Assets/Scripts/checkpoint_con.cs" Line="21" Column="92" />
      <File FileName="Assets/Scripts/EnemyScript.cs" Line="77" Column="17" />
      <File FileName="Assets/Scripts/airEnemy.cs" Line="9" Column="29" />
    </Files>
    <Pads>
      <Pad Id="ProjectPad">
        <State name="__root__">
          <Node name="FinalProject" expanded="True" selected="True" />
        </State>
      </Pad>
    </Pads>
  </MonoDevelop.Ide.Workbench>
  <MonoDevelop.Ide.DebuggingService.PinnedWatches />
  <MonoDevelop.Ide.Workspace ActiveConfiguration="Debug" />
  <MonoDevelop.Ide.ItemProperties.Assembly-CSharp PreferredExecutionTarget="5582f887-eb30-4c4d-a452-e69326cdb000" />
  <MonoDevelop.Ide.DebuggingService.Breakpoints>
    <BreakpointStore />
  </MonoDevelop.Ide.DebuggingService.Breakpoints>
  <MultiItemStartupConfigurations />
</Properties>